<?xml version="1.0" encoding="utf-8"?>
<savedqueries xmlns:xsi="http://www.w3.org/2001/XMLSchema-instance">
  <savedquery>
    <IsCustomizable>1</IsCustomizable>
    <CanBeDeleted>0</CanBeDeleted>
    <isquickfindquery>0</isquickfindquery>
    <isprivate>0</isprivate>
    <isdefault>0</isdefault>
    <savedqueryid>{8f0a7546-b317-4c26-a5f3-7997e52a2632}</savedqueryid>
    <layoutxml>
      <grid name="resultset" jump="msmedia_name" select="1" icon="1" preview="1">
        <row name="result" id="msmedia_dispenserid">
          <cell name="msmedia_name" width="300" />
          <cell name="createdon" width="125" />
        </row>
      </grid>
    </layoutxml>
    <querytype>0</querytype>
    <fetchxml>
      <fetch version="1.0" mapping="logical">
        <entity name="msmedia_dispenser">
          <attribute name="msmedia_dispenserid" />
          <attribute name="msmedia_name" />
          <attribute name="createdon" />
          <order attribute="msmedia_name" descending="false" />
          <filter type="and">
            <condition attribute="statecode" operator="eq" value="1" />
          </filter>
        </entity>
      </fetch>
    </fetchxml>
    <IntroducedVersion>1.0.2.7</IntroducedVersion>
    <LocalizedNames>
      <LocalizedName description="Inactive Dispensers" languagecode="1033" />
    </LocalizedNames>
  </savedquery>
</savedqueries>